readwise_sdk/__init__.py
readwise_sdk/_base_client.py
readwise_sdk/_client.py
readwise_sdk/_compat.py
readwise_sdk/_constants.py
readwise_sdk/_exceptions.py
readwise_sdk/_files.py
readwise_sdk/_models.py
readwise_sdk/_qs.py
readwise_sdk/_resource.py
readwise_sdk/_response.py
readwise_sdk/_streaming.py
readwise_sdk/_types.py
readwise_sdk/_version.py
readwise_sdk/py.typed
readwise_sdk/_utils/__init__.py
readwise_sdk/_utils/_logs.py
readwise_sdk/_utils/_proxy.py
readwise_sdk/_utils/_reflection.py
readwise_sdk/_utils/_streams.py
readwise_sdk/_utils/_sync.py
readwise_sdk/_utils/_transform.py
readwise_sdk/_utils/_typing.py
readwise_sdk/_utils/_utils.py
readwise_sdk/lib/.keep
readwise_sdk/resources/__init__.py
readwise_sdk/resources/auth.py
readwise_sdk/resources/books.py
readwise_sdk/resources/highlights.py
readwise_sdk/types/__init__.py
readwise_sdk/types/book_list_params.py
readwise_sdk/types/book_list_response.py
readwise_sdk/types/highlight_list_params.py
readwise_sdk/types/highlight_list_response.py
readwise_sdk-0.1.0a2.dist-info/METADATA
readwise_sdk-0.1.0a2.dist-info/WHEEL
readwise_sdk-0.1.0a2.dist-info/licenses/LICENSE
readwise_sdk-0.1.0a2.dist-info/RECORD
